[{"image_link": "https://scontent-arn2-1.xx.fbcdn.net/v/t39.30808-6/495566398_1251790956950004_9052348402516664471_n.jpg?stp=dst-jpg_s2048x2048_tt6&_nc_cat=103&ccb=1-7&_nc_sid=75d36f&_nc_ohc=iFAfnzWixyAQ7kNvwHeukHH&_nc_oc=AdnrjnDoDsgTBCqipq6ngv_zBxKDok8O5cf4ResYy-9VlCbMCZbEUnOQRANSV9mtK_s&_nc_zt=23&_nc_ht=scontent-arn2-1.xx&_nc_gid=Dacon-xD07IZ9cKlVNxHMQ&oh=00_AfMFb4ISHjJz_1Kwosefhn7zUzodFT1vTbd-Q1UZ6_4O_Q&oe=6848FB22", "url": "https://www.facebook.com/events/1692130761397455/", "js_timestamp": "2025-06-06T00:00:00+00:00", "formatted_start_date": "Friday 06 June", "title": "Department Festival 2025"}, {"image_link": "https://billetto.imgix.net/bt82mvlg6ceg3jknbbomxe2pnpkx?w=1200&h=675&fit=crop&auto=compress%2Cformat&rect=0%2C0%2C2048%2C1152&s=03d782288b1e4fe46dfffea19c82f95d", "url": "https://billetto.se/e/rooftop-reverie-22-03-biljetter-1306802?utm_campaign=websites&utm_content=SE+805283&utm_medium=publishers&utm_source=billetto+advertising", "js_timestamp": "2025-06-06T20:00:00+00:00", "formatted_start_date": "Friday 06 June", "title": "Rooftop Reverie / 22-03"}, {"image_link": "https://scontent-arn2-1.xx.fbcdn.net/v/t39.30808-6/490106866_1245391934136663_6462075311945713150_n.jpg?_nc_cat=102&ccb=1-7&_nc_sid=75d36f&_nc_ohc=F028AgrguMYQ7kNvwHwYMV3&_nc_oc=AdnevpZ5M0IupLo5eZVFOfBRv7wEmIB45izDH2L3VR_995zmKa_3Wyyqn4AtRbN8kfY&_nc_zt=23&_nc_ht=scontent-arn2-1.xx&_nc_gid=u3w7OM5cKH6NydTWZbAvlg&oh=00_AfMG_9EgiS26S4nCINmnndyiHr4wqr5CF9zo5PfIEu74hQ&oe=6848E0B5", "url": "https://www.facebook.com/events/891189969745745/", "js_timestamp": "2025-06-07T00:00:00+00:00", "formatted_start_date": "Saturday 07 June", "title": "ZENITH daytime festival 4.0"}, {"image_link": "https://scontent-arn2-1.xx.fbcdn.net/v/t39.30808-6/487358625_122237112074063828_1561952196322286339_n.jpg?_nc_cat=109&ccb=1-7&_nc_sid=75d36f&_nc_ohc=9GFnMgLGOAMQ7kNvwEYP79M&_nc_oc=Adn2-U_qULqpebjxBoN2IITM5RAsniqOG1oFbdBqWAuyxkfCF6Rf68G4j6f9oWePYgg&_nc_zt=23&_nc_ht=scontent-arn2-1.xx&_nc_gid=Tk34y8e-fITSoEBMC5oFyg&oh=00_AfPueqsQeM61fXYhGveQVkuYeHKDqqSUvNTFHG_USSIPEQ&oe=6848D8D3", "url": "https://www.facebook.com/events/670990325419039/", "js_timestamp": "2025-06-07T00:00:00+00:00", "formatted_start_date": "Saturday 07 June", "title": "AIZ PROJECT - Reb\u016bke"}, {"image_link": "https://billetto.imgix.net/m3m8m13kfqc5votyvnvaygqe4q76?w=1200&h=675&fit=crop&auto=compress%2Cformat&rect=0%2C2114%2C2479%2C1394&s=d1a34d3306bca2b65ecb20fd40f20c2b", "url": "https://billetto.se/e/elektroweekend-6-0-biljetter-1266299?utm_campaign=websites&utm_content=SE+805283&utm_medium=publishers&utm_source=billetto+advertising", "js_timestamp": "2025-06-07T18:00:00+00:00", "formatted_start_date": "Saturday 07 June", "title": "ELEKTROWEEKEND 6:0"}, {"image_link": "https://scontent-arn2-1.xx.fbcdn.net/v/t39.30808-6/487943338_673981452045231_6409614706646425980_n.jpg?_nc_cat=102&ccb=1-7&_nc_sid=75d36f&_nc_ohc=ONnqDF8Q0SkQ7kNvwFhk2aS&_nc_oc=Adk_92YElRe9gKMo8Q3Sd2mN_u_phbld9KcB-hmEaiBPIGQQgyR00JFy9Wqzms3RdtQ&_nc_zt=23&_nc_ht=scontent-arn2-1.xx&_nc_gid=QbzIzlFn6Ce2-iqlloDTwA&oh=00_AfMzaNrsvogprgzywNmDldHSymMjIEVe6iQTlkJ1xbslRA&oe=6848EFA4", "url": "https://www.facebook.com/events/662915966180828/", "js_timestamp": "2025-06-13T00:00:00+00:00", "formatted_start_date": "Friday 13 June", "title": "What A View / June 13+14"}, {"image_link": "https://scontent-arn2-1.xx.fbcdn.net/v/t39.30808-6/488420063_990877649854036_4951937102188449552_n.jpg?_nc_cat=107&ccb=1-7&_nc_sid=75d36f&_nc_ohc=4Y5D4L26U-wQ7kNvwEtfWbJ&_nc_oc=Adnh_Lzh6cXSVqxbLNSQyevzGRV8PZ87FtfwJu1I39LEezrZPzW7u2BbtwiC2b3Bp14&_nc_zt=23&_nc_ht=scontent-arn2-1.xx&_nc_gid=rUWMJMR1m1by1dYDEvr0QA&oh=00_AfP_nogbtggocjZf0u3cgrPBfP9F-aHAGI04w8ji6ncl2Q&oe=6848FAD1", "url": "https://www.facebook.com/events/1890033175130263/", "js_timestamp": "2025-06-13T00:00:00+00:00", "formatted_start_date": "Friday 13 June", "title": "SPACE 92 X POPOF by DEMAND | Slaktkyrkan"}, {"image_link": "https://billetto.imgix.net/vzncawv83qsqz3nt9n9t6y88maqd?w=1200&h=675&fit=crop&auto=compress%2Cformat&rect=0%2C1%2C2665%2C1499&s=0420e89215e8227a25ba3f0dc2550071", "url": "https://billetto.se/e/originoftrance-next-step-beatbizarre-tegma-pumpehuset-biljetter-1110254?utm_campaign=websites&utm_content=SE+805283&utm_medium=publishers&utm_source=billetto+advertising", "js_timestamp": "2025-06-13T17:11:16.080694+00:00", "formatted_start_date": "Friday 13 June", "title": "ORIGINOFTRANCE- NEXT STEP - BEATBIZARRE/TEGMA @PUMPEHUSET"}, {"image_link": "https://billetto.imgix.net/1mrahyk0vc96c5prd38q3qpljnft?w=1200&h=675&fit=crop&auto=compress%2Cformat&rect=71%2C0%2C1906%2C1072&s=319210511353eb4bfb8f23b104e9f690", "url": "https://billetto.se/e/mohriska-presents-hedda-stenberg-season-closing-biljetter-1283901?utm_campaign=websites&utm_content=SE+805283&utm_medium=publishers&utm_source=billetto+advertising", "js_timestamp": "2025-06-13T20:00:00+00:00", "formatted_start_date": "Friday 13 June", "title": "MOHRISKA presents HEDDA STENBERG | Season Closing"}, {"image_link": "https://billetto.imgix.net/4v683xwznfs1wf8csic4vtkeihx5?w=1200&h=675&fit=crop&auto=compress%2Cformat&rect=0%2C0%2C1920%2C1080&s=0f85beb4a77e529983e0ce77ffc2924b", "url": "https://billetto.se/e/space-92-popof-france-biljetter-1266507?utm_campaign=websites&utm_content=SE+805283&utm_medium=publishers&utm_source=billetto+advertising", "js_timestamp": "2025-06-13T20:00:00+00:00", "formatted_start_date": "Friday 13 June", "title": "SPACE 92 & POPOF (France)"}, {"image_link": "https://scontent-arn2-1.xx.fbcdn.net/v/t39.30808-6/483891161_1181607776682552_8043495761527606687_n.jpg?_nc_cat=103&ccb=1-7&_nc_sid=75d36f&_nc_ohc=MNH_PwBIsHEQ7kNvwFanzcF&_nc_oc=AdmbUJ-9wrrRdtLDS9C31h5ItMViUWP0wjBEAp_NPDXKEX4rdDsW5F5DCEdiCknJIdU&_nc_zt=23&_nc_ht=scontent-arn2-1.xx&_nc_gid=rPDJmdfBESJpBra1pgk98g&oh=00_AfMn3cXtS3F9bps6Cg01qNpI_Zfh0ZFHpU9_rH2EMKBfZw&oe=6848E756", "url": "https://www.facebook.com/events/1662977134297912/", "js_timestamp": "2025-06-14T00:00:00+00:00", "formatted_start_date": "Saturday 14 June", "title": "Skogen kallar Open Air 2025"}, {"image_link": "https://billetto.imgix.net/s3adjp27k2mqcjs3k7hgr4unf0lv?w=1200&h=675&fit=crop&auto=compress%2Cformat&rect=67%2C0%2C1787%2C1005&s=5298954866fa3c90bc2b9e0704019181", "url": "https://billetto.se/e/acid-robot-label-night-biljetter-1306481?utm_campaign=websites&utm_content=SE+805283&utm_medium=publishers&utm_source=billetto+advertising", "js_timestamp": "2025-06-14T20:00:00+00:00", "formatted_start_date": "Saturday 14 June", "title": "Acid Robot Label Night"}, {"image_link": "https://billetto.imgix.net/ob43m2yfecfifu0u1dgk4kiguf52?w=1200&h=675&fit=crop&auto=compress%2Cformat&rect=67%2C0%2C1787%2C1005&s=1d32fcbbcce4c252041210b14df394eb", "url": "https://billetto.se/e/skogen-kallar-open-air-2025-biljetter-1145620?utm_campaign=websites&utm_content=SE+805283&utm_medium=publishers&utm_source=billetto+advertising", "js_timestamp": "2025-06-14T21:00:00+00:00", "formatted_start_date": "Saturday 14 June", "title": "Skogen Kallar  Open Air 2025"}, {"image_link": "https://scontent-arn2-1.xx.fbcdn.net/v/t39.30808-6/494697684_1102574601908585_685528736175432219_n.jpg?_nc_cat=102&ccb=1-7&_nc_sid=75d36f&_nc_ohc=CuDr53YqLfkQ7kNvwFdZFDv&_nc_oc=Adk9p6IqzabGcohjVVKmbt6F4Nriy5K8kWNWuioI1_VphfXcp_IaRHxI9piLNJqwm7M&_nc_zt=23&_nc_ht=scontent-arn2-1.xx&_nc_gid=4y6WRk5eFYV2tehuKKxOFw&oh=00_AfOzHnPh2Fvy6Y6hHce1GLb7VyuwB3CCnjvcNK4obJimMA&oe=68490EC8", "url": "https://www.facebook.com/events/2384636508535102/", "js_timestamp": "2025-06-20T00:00:00+00:00", "formatted_start_date": "Friday 20 June", "title": "A Midsummer Nights Rave "}, {"image_link": "https://scontent-arn2-1.xx.fbcdn.net/v/t39.30808-6/504003766_1231581108978166_8902547790978789439_n.jpg?_nc_cat=101&ccb=1-7&_nc_sid=75d36f&_nc_ohc=uECTUqbPmRIQ7kNvwEe2n6L&_nc_oc=Adll7DIZZtal2bxvGMwGR06FBcFKDQ0t8t5HND70VAjE2d_REnO8jEE7cyrI5rD29xM&_nc_zt=23&_nc_ht=scontent-arn2-1.xx&_nc_gid=6j-IfBSL0TKxpkSBh1bzEA&oh=00_AfP3PsloTPnKYyrh8dwWkW41MchsCXkiwVMhZc4beiQ-5A&oe=6848D989", "url": "https://www.facebook.com/events/1769347973649469/", "js_timestamp": "2025-06-20T00:00:00+00:00", "formatted_start_date": "Friday 20 June", "title": "BRONX MIDSUMMER * TECHNO WOODSTOCK OPEN AIR * Franz J\u00e4ger * Younger Than Me * OSO.STHLM * Nous Klear"}, {"image_link": "https://scontent-arn2-1.xx.fbcdn.net/v/t39.30808-6/497835638_998860979000379_8374563647965577033_n.jpg?_nc_cat=106&ccb=1-7&_nc_sid=75d36f&_nc_aid=0&_nc_ohc=TvOahzDwPDQQ7kNvwG0hO72&_nc_oc=AdnqlVDvMATiN4TAiAu5yjZAhypyNqCk_TdoF6dxEPlCUwKVGpLFp1jjSONOiomJKj0&_nc_zt=23&_nc_ht=scontent-arn2-1.xx&_nc_gid=orDtnagZSroG25FRLDnapw&oh=00_AfNX3aTlTKYwk4hlj8Bfz_vQA9qV04RQsolcKx8tyji7fw&oe=6848EBD6", "url": "https://www.facebook.com/events/1744580669829490/", "js_timestamp": "2025-06-20T00:00:00+00:00", "formatted_start_date": "Friday 20 June", "title": "MIDSOMMAR 2025 \u2013 OPEN AIR"}, {"image_link": "https://scontent-arn2-1.xx.fbcdn.net/v/t39.30808-6/467671810_8951112171617301_626831552952023369_n.jpg?_nc_cat=101&ccb=1-7&_nc_sid=75d36f&_nc_ohc=ULwXoVLpeKsQ7kNvwE7hb0l&_nc_oc=AdnWs8ax1PTiC7_S4uTQe8m_yqFAWMBlYdySLN3ATShRDCR8bYbb3uCzSVYtf4bgUso&_nc_zt=23&_nc_ht=scontent-arn2-1.xx&_nc_gid=9y5I1fmIbm0tX-mEADBBGw&oh=00_AfOV-eqQB5lFY7QaTBYyUD1chZR2nhALDM_eXJatx59Nww&oe=6848E2A8", "url": "https://www.facebook.com/events/513127173271474/", "js_timestamp": "2025-06-20T00:00:00+00:00", "formatted_start_date": "Friday 20 June", "title": "Technostate Boat Party Flyttat"}, {"image_link": "https://billetto.imgix.net/9do3wdsosq2k7lu1xas4ax60s1f4?w=1200&h=675&fit=crop&auto=compress%2Cformat&rect=0%2C0%2C1920%2C1080&s=a7ea071123df2d443652deab32ac7507", "url": "https://billetto.se/e/midsommar-2025-open-air-biljetter-1307653?utm_campaign=websites&utm_content=SE+805283&utm_medium=publishers&utm_source=billetto+advertising", "js_timestamp": "2025-06-20T21:00:00+00:00", "formatted_start_date": "Friday 20 June", "title": "MIDSOMMAR 2025 - OPEN AIR"}, {"image_link": "https://scontent-arn2-1.xx.fbcdn.net/v/t39.30808-6/491934066_628213053541608_927118269871647771_n.jpg?_nc_cat=105&ccb=1-7&_nc_sid=75d36f&_nc_ohc=AfWeRe9eVrEQ7kNvwExmYsQ&_nc_oc=AdnzK9SUvIJrLyA1eLXNaj__5IA9vH9ll-xV_H5Cm240KkST--ghDGidhWVFdMUFq4w&_nc_zt=23&_nc_ht=scontent-arn2-1.xx&_nc_gid=QjH_iSSEY32u78nueoxVBA&oh=00_AfOX0nwsXviNzN_eDNeQ4n2WcyB51raZFGidAAG-22RgvA&oe=6848E950", "url": "https://www.facebook.com/events/1362970958286003/", "js_timestamp": "2025-06-21T00:00:00+00:00", "formatted_start_date": "Saturday 21 June", "title": "\ud83d\udd25 Midsummer 2025 \ud83d\udd25 OPEN AIR "}, {"image_link": "https://billetto.imgix.net/jqpqddzaixd6ujof5prju7r1pg7j?w=1200&h=675&fit=crop&auto=compress%2Cformat&rect=0%2C0%2C1399%2C787&s=1f69ce9a1c17516309e704112572a9ff", "url": "https://billetto.se/e/mittsommerfeier-musikstaden-biljetter-1271025?utm_campaign=websites&utm_content=SE+805283&utm_medium=publishers&utm_source=billetto+advertising", "js_timestamp": "2025-06-21T16:00:00+00:00", "formatted_start_date": "Saturday 21 June", "title": "Mittsommerfeier - Musikstaden "}, {"image_link": "https://billetto.imgix.net/v3oxmp40n238bapq1yylk68ugz80?w=1200&h=675&fit=crop&auto=compress%2Cformat&rect=0%2C6%2C4600%2C2588&s=c3dbfcc46c85235d7fb4e42db8305c31", "url": "https://billetto.se/e/midsummer-2025-open-air-biljetter-1272203?utm_campaign=websites&utm_content=SE+805283&utm_medium=publishers&utm_source=billetto+advertising", "js_timestamp": "2025-06-21T20:00:00+00:00", "formatted_start_date": "Saturday 21 June", "title": " Midsummer 2025 OPEN AIR"}, {"image_link": "https://scontent-arn2-1.xx.fbcdn.net/v/t39.30808-6/503095502_1012200020988013_8243111285726266858_n.jpg?_nc_cat=109&ccb=1-7&_nc_sid=75d36f&_nc_ohc=SG3ZmelLlngQ7kNvwE-yIun&_nc_oc=Admj_u3CxJDGfmiYgKb6pKnP3C-PYUtH1ixD2-ZXSwN5Uu_4iFlxWBEU1F8_X2olU1w&_nc_zt=23&_nc_ht=scontent-arn2-1.xx&_nc_gid=gmzGpKdA4qy6k7Q5zq6lBA&oh=00_AfOnR1oU_bF-9RkCVMZ24TIosdAca1d3pcmt9xqYloruyg&oe=6848E96F", "url": "https://www.facebook.com/events/1653039732044736/", "js_timestamp": "2025-06-27T00:00:00+00:00", "formatted_start_date": "Friday 27 June", "title": "Zenit Festival"}, {"image_link": "https://scontent-arn2-1.xx.fbcdn.net/v/t39.30808-6/491762381_1180776297169361_6341726110592648756_n.jpg?stp=cp6_dst-jpg_tt6&_nc_cat=111&ccb=1-7&_nc_sid=75d36f&_nc_ohc=iJ3FEz8pqIwQ7kNvwEe-dfD&_nc_oc=AdkYG5jLkTRcNFW_74LfMJKqHGYiW_mRNeu9ZJMIcSbzTgNi6EvAv7fAECf-Q2szZVI&_nc_zt=23&_nc_ht=scontent-arn2-1.xx&_nc_gid=IdcMI813NGqNKQPDsHxYVA&oh=00_AfMf9KkV_r_7uT8T4kpCKY76W8UHlGn14TnwePjYktpphw&oe=6848FD8F", "url": "https://www.facebook.com/events/1391307178545233/", "js_timestamp": "2025-06-27T00:00:00+00:00", "formatted_start_date": "Friday 27 June", "title": "IBNE @ Kvarteret [NYMED (TOYZ, Pornceptual), HARAMI, ANDEMON]"}, {"image_link": "https://billetto.imgix.net/ok1i4c42iqdpkz3gq4pvqo418ssx?w=1200&h=675&fit=crop&auto=compress%2Cformat&rect=67%2C0%2C1787%2C1005&s=3033fdf78a9e6212c15058d1be7893c3", "url": "https://billetto.se/e/ibne-w-nymed-fr-harami-andemon-biljetter-1268172?utm_campaign=websites&utm_content=SE+805283&utm_medium=publishers&utm_source=billetto+advertising", "js_timestamp": "2025-06-27T20:00:00+00:00", "formatted_start_date": "Friday 27 June", "title": "IBNE w/ Nymed (FR), Harami, Andemon"}, {"image_link": "https://scontent-arn2-1.xx.fbcdn.net/v/t39.30808-6/502516414_1289181313218038_8060616973868508832_n.jpg?_nc_cat=102&ccb=1-7&_nc_sid=75d36f&_nc_ohc=jehsIc1wrt0Q7kNvwHU735w&_nc_oc=AdlJD0zV1oRy-Lz47t3OOsnXsath-zk3s4g7gaQWZL8JwAu0qTbeeoRE-XGNP8b-11g&_nc_zt=23&_nc_ht=scontent-arn2-1.xx&_nc_gid=nzT1ma59tiYhb_V3m3UwUA&oh=00_AfMjbG3TFYjdsn38yffH48a42ImSQWNsCT0ccV0_nZnyWA&oe=6848FC25", "url": "https://www.facebook.com/events/1205901867934432/", "js_timestamp": "2025-06-28T00:00:00+00:00", "formatted_start_date": "Saturday 28 June", "title": "Sommarnatt "}, {"image_link": "https://scontent-arn2-1.xx.fbcdn.net/v/t39.30808-6/500223846_686619574097647_8078520327681229042_n.jpg?_nc_cat=103&ccb=1-7&_nc_sid=75d36f&_nc_ohc=Z1FupJ9oLAgQ7kNvwHKp9AH&_nc_oc=AdmD5Sp7xVZEWFyPiqqRaHJbzj6jq1GwV24tAsNiEo1_-oQnH-Y55ROFSSjG0A-zR80&_nc_zt=23&_nc_ht=scontent-arn2-1.xx&_nc_gid=8JWOoHlHU3ddl4NOokOA8w&oh=00_AfP9fAiEIxI293wEjBwa7cOTkyRfzCFKQZTdTUm2XMamwA&oe=6849058A", "url": "https://www.facebook.com/events/739661198522975/", "js_timestamp": "2025-06-28T00:00:00+00:00", "formatted_start_date": "Saturday 28 June", "title": "Technostamp 15 | Resebyr\u00e5n"}, {"image_link": "https://scontent-arn2-1.xx.fbcdn.net/v/t39.30808-6/503448892_1231375882332022_4027768699202012002_n.jpg?stp=cp6_dst-jpg_tt6&_nc_cat=110&ccb=1-7&_nc_sid=75d36f&_nc_ohc=OCXUNVNq8bkQ7kNvwFl8KkP&_nc_oc=AdkMER7iMMk1uwP_nrZR2DsS3D5GO6k3oAv2UnjuQUevuKffChftxjGLyjld-VkpoRk&_nc_zt=23&_nc_ht=scontent-arn2-1.xx&_nc_gid=uqgZO2gnSqhlsLmp5PdSow&oh=00_AfNx7bpGohycPh4GYin7cF1KNbYnoXoab_fjQTVfO_R_BA&oe=6848EB3B", "url": "https://www.facebook.com/events/1640316790008122/", "js_timestamp": "2025-06-28T00:00:00+00:00", "formatted_start_date": "Saturday 28 June", "title": "BRONX UNDERGROUND // TUBT\u00d6MMNING // Info kommer i veckan"}, {"image_link": "https://billetto.imgix.net/d9mrkb93gwztw1qlaj8nefavw884?w=1200&h=675&fit=crop&auto=compress%2Cformat&rect=67%2C0%2C1787%2C1005&s=b2f79b5b270ed6ad01119b5f74076ab9", "url": "https://billetto.se/e/four-6-x-technohall-x-kibe-biljetter-1266512?utm_campaign=websites&utm_content=SE+805283&utm_medium=publishers&utm_source=billetto+advertising", "js_timestamp": "2025-06-28T20:00:00+00:00", "formatted_start_date": "Saturday 28 June", "title": "Four 6 X Technohall X KIBE"}, {"image_link": "https://billetto.imgix.net/frxh8pi3v76q2bw0cws6np0lqnd7?w=1200&h=675&fit=crop&auto=compress%2Cformat&rect=0%2C0%2C1920%2C1080&s=6db3402f04d84057b3ae6d57ce27fc3e", "url": "https://billetto.se/e/resebyran-technostamp-15-biljetter-1298845?utm_campaign=websites&utm_content=SE+805283&utm_medium=publishers&utm_source=billetto+advertising", "js_timestamp": "2025-06-28T21:00:00+00:00", "formatted_start_date": "Saturday 28 June", "title": "Resebyr\u00e5n | Technostamp 15"}, {"image_link": "https://billetto.imgix.net/ms0gb1mrzycl0c9nvt02xidzzxlv?w=1200&h=675&fit=crop&auto=compress%2Cformat&rect=0%2C0%2C4000%2C2250&s=93af1aa00c38989cf0900c4ca005c134", "url": "https://billetto.se/e/techno-stockholm-inner-call-biljetter-1299942?utm_campaign=websites&utm_content=SE+805283&utm_medium=publishers&utm_source=billetto+advertising", "js_timestamp": "2025-07-04T20:00:00+00:00", "formatted_start_date": "Friday 04 July", "title": "TECHNO STOCKHOLM INNER CALL"}, {"image_link": "https://scontent-arn2-1.xx.fbcdn.net/v/t39.30808-6/492888064_122246677064063828_7240548758548892425_n.jpg?_nc_cat=104&ccb=1-7&_nc_sid=75d36f&_nc_ohc=CO5cGT8By0kQ7kNvwE4bwaK&_nc_oc=AdmaYRVuR6Efq-CzJj9ISuWfs9qVhuzPqpUrU3hzHSs-yBXkgPg0FZx7hVGCknBeIdU&_nc_zt=23&_nc_ht=scontent-arn2-1.xx&_nc_gid=9nO7gmzxLKIaKv3i6RIebw&oh=00_AfM-gmzvJWRgvSXD-iwPVPOt3hfS3PwaaIth4OhIVqXbZQ&oe=6848FFF1", "url": "https://www.facebook.com/events/1056667562992752/", "js_timestamp": "2025-07-11T00:00:00+00:00", "formatted_start_date": "Friday 11 July", "title": "AIZ PROJECT - Cassian"}, {"image_link": "https://billetto.imgix.net/pc9vlpmw1r7hpqupiv51r8fjikfs?w=1200&h=675&fit=crop&auto=compress%2Cformat&rect=223%2C0%2C2946%2C1657&s=6d979943f0d65afb0c307c0f5d48e62a", "url": "https://billetto.se/e/veravera-fred-s-biljetter-1302653?utm_campaign=websites&utm_content=SE+805283&utm_medium=publishers&utm_source=billetto+advertising", "js_timestamp": "2025-07-19T20:00:00+00:00", "formatted_start_date": "Saturday 19 July", "title": "VERAVERA @ Fred\u00b4s"}, {"image_link": "https://billetto.imgix.net/5w8gnljuru6zw7cmf41pvfrgonqe?w=1200&h=675&fit=crop&auto=compress%2Cformat&rect=0%2C0%2C800%2C450&s=982f396589d528086d65e5f39220c8b8", "url": "https://billetto.se/e/elektrified-biljetter-1273052?utm_campaign=websites&utm_content=SE+805283&utm_medium=publishers&utm_source=billetto+advertising", "js_timestamp": "2025-07-19T21:00:00+00:00", "formatted_start_date": "Saturday 19 July", "title": "Elektrified"}, {"image_link": "https://scontent-arn2-1.xx.fbcdn.net/v/t39.30808-6/497577285_1239224731546534_8191853151681050020_n.jpg?_nc_cat=108&ccb=1-7&_nc_sid=75d36f&_nc_ohc=MM51B5ydSjEQ7kNvwHECPv2&_nc_oc=Adm6frp2TW1yfYNcOwpRklXWLgxYRgpPTHKyCksFVwS6J_cBT6B-pcdRz2Pj_eftdJg&_nc_zt=23&_nc_ht=scontent-arn2-1.xx&_nc_gid=K1hS81L8h4iuLYblQbrrNQ&oh=00_AfPmfJnds_feKPsYa1dUoLEera2SN7VCHovPhvXc7IWSjg&oe=684904AF", "url": "https://www.facebook.com/events/1461165594855485/", "js_timestamp": "2025-07-25T00:00:00+00:00", "formatted_start_date": "Friday 25 July", "title": "420 Boat Party I 420 Residents I 25 juli"}, {"image_link": "https://billetto.imgix.net/b5mag1huv4vnrt1jd4qcf582p45n?w=1200&h=675&fit=crop&auto=compress%2Cformat&rect=67%2C0%2C1787%2C1005&s=b65683e9279ed66a12517210b1fd1a7a", "url": "https://billetto.se/e/klanglandet-festival-2025-biljetter-1166339?utm_campaign=websites&utm_content=SE+805283&utm_medium=publishers&utm_source=billetto+advertising", "js_timestamp": "2025-07-25T10:00:00+00:00", "formatted_start_date": "Friday 25 July", "title": "Klanglandet Festival 2025"}, {"image_link": "https://billetto.imgix.net/a96pge7vhj4tndygbh4y05lg9xeb?w=1200&h=675&fit=crop&auto=compress%2Cformat&rect=0%2C0%2C1920%2C1080&s=4742f804fe9502da4f3ae895a522291b", "url": "https://billetto.se/e/420-boat-party-biljetter-1268094?utm_campaign=websites&utm_content=SE+805283&utm_medium=publishers&utm_source=billetto+advertising", "js_timestamp": "2025-07-25T18:00:00+00:00", "formatted_start_date": "Friday 25 July", "title": "420 Boat Party"}, {"image_link": "https://scontent-arn2-1.xx.fbcdn.net/v/t39.30808-6/493539765_1235501438575087_3393846796220679714_n.jpg?_nc_cat=103&ccb=1-7&_nc_sid=75d36f&_nc_ohc=DD7QBPOtsBQQ7kNvwGl0CQn&_nc_oc=AdlBDeG2RYbO4mpxpqfs4gIoDinIBIIVJeUuI8K4ndt947faF49MrWxD6QzVUD9BVcQ&_nc_zt=23&_nc_ht=scontent-arn2-1.xx&_nc_gid=Fr9xq0cLgxatgqGk5AkTBQ&oh=00_AfOUOIUOK9tf9JahgyOk_iYWP8KfeCG7esDoYrBZfX2byA&oe=6848ECB9", "url": "https://www.facebook.com/events/1734533720744446/", "js_timestamp": "2025-07-26T00:00:00+00:00", "formatted_start_date": "Saturday 26 July", "title": "Gate TECHNO BOAT is BACK"}, {"image_link": "https://scontent-arn2-1.xx.fbcdn.net/v/t39.30808-6/503879402_1231140215688922_63259165999188212_n.jpg?_nc_cat=103&ccb=1-7&_nc_sid=75d36f&_nc_ohc=cSRPRS2UnQ4Q7kNvwEIZn9y&_nc_oc=Adka-OaqNXcV3G22AVMML_w8rms_tsSqXx2W8iBmxs1vvpUrmEZ96K6Nf67SewSJ9vs&_nc_zt=23&_nc_ht=scontent-arn2-1.xx&_nc_gid=Y8Kli_JIm6wxvzMXOnEHvw&oh=00_AfNbcoilZA-i0t0KzKoO92HdcHAqB6qLfClN0tigNVTCWw&oe=684901FD", "url": "https://www.facebook.com/events/3620841384713929/", "js_timestamp": "2025-07-26T00:00:00+00:00", "formatted_start_date": "Saturday 26 July", "title": "BRONX UNDERGROUND OPEN AIR"}, {"image_link": "https://scontent-arn2-1.xx.fbcdn.net/v/t39.30808-6/499805305_1011705534442389_1148444532242622332_n.jpg?stp=cp6_dst-jpg_tt6&_nc_cat=109&ccb=1-7&_nc_sid=75d36f&_nc_ohc=al1avMJH8HIQ7kNvwECcttk&_nc_oc=AdlmGFNH_iG5PWC_s3OrUjeVd7ocLXShtdvWFuQVCNXbmvcufIGZBlPH2U5DvZcOL6I&_nc_zt=23&_nc_ht=scontent-arn2-1.xx&_nc_gid=xEnoz7GZLPkYjB7MfdBRSQ&oh=00_AfMdt-i4cA7S7Wc7Lwf9jmjWmFxWyMceTxVN1FD3sn0N0Q&oe=68490B5D", "url": "https://www.facebook.com/events/724799986558382/", "js_timestamp": "2025-08-02T00:00:00+00:00", "formatted_start_date": "Saturday 02 August", "title": "CLEAN & BRONX SAUNA in corp. KinkClub, Nachspiel, Berlin Natt Present PRIDE outdoor celebration"}, {"image_link": "https://scontent-arn2-1.xx.fbcdn.net/v/t39.30808-6/489928610_10162712786074292_230868006566021788_n.jpg?_nc_cat=103&ccb=1-7&_nc_sid=75d36f&_nc_ohc=mXJMQj350lcQ7kNvwH85lqO&_nc_oc=AdlMhSf0QVshcZqf1jtdPk2F6G0X8uGlH3Ups5a6UJKS09hUUonMwOnZS5OCF2mUJfw&_nc_zt=23&_nc_ht=scontent-arn2-1.xx&_nc_gid=mnwKDC3rdp1AF8iO-KNwXg&oh=00_AfO635g-fY0PU47Fz_pszKzurcV-HGFGStwc9PL6L1R9dw&oe=6848DDD9", "url": "https://www.facebook.com/events/1196014038892980/", "js_timestamp": "2025-08-02T00:00:00+00:00", "formatted_start_date": "Saturday 02 August", "title": "IBNE x LLIPS PRIDE 2025"}, {"image_link": "https://billetto.imgix.net/hjgumxn29rano6zbpk2pnaz7qd51?w=1200&h=675&fit=crop&auto=compress%2Cformat&rect=0%2C214%2C2048%2C1152&s=610961e13c2c2d05da8d159119b5d342", "url": "https://billetto.se/e/clean-bronx-nya-bastun-presents-pride-party-saturday-august-2th-biljetter-1287907?utm_campaign=websites&utm_content=SE+805283&utm_medium=publishers&utm_source=billetto+advertising", "js_timestamp": "2025-08-02T21:00:00+00:00", "formatted_start_date": "Saturday 02 August", "title": "CLEAN & BRONX - Nya Bastun presents PRIDE Party Saturday august 2th"}, {"image_link": "https://scontent-arn2-1.xx.fbcdn.net/v/t39.30808-6/497824566_1254414710017876_3013805225766760194_n.jpg?_nc_cat=109&ccb=1-7&_nc_sid=75d36f&_nc_ohc=hT9y9Wyc-_gQ7kNvwF4psUG&_nc_oc=AdnGoOF4wO_nPJ2eTpnsH4O47ZMXGS9d9zTFARZFVAjAgSeLeOBEiN_dS_46qsOEqAY&_nc_zt=23&_nc_ht=scontent-arn2-1.xx&_nc_gid=gS4qW7kBS825jl0v-rXK-Q&oh=00_AfPkENEj0rIgkaJjKi7AdFXx-F7msj60Zu2WizfLoiW3zw&oe=6848DDDA", "url": "https://www.facebook.com/events/678049088243553/", "js_timestamp": "2025-08-08T00:00:00+00:00", "formatted_start_date": "Friday 08 August", "title": "L\u00e5ngholmen Open Air - Chris Avantgarde - Neelix "}, {"image_link": "https://scontent-arn2-1.xx.fbcdn.net/v/t39.30808-6/476923723_1161931805316816_7120402610756809254_n.jpg?_nc_cat=106&ccb=1-7&_nc_sid=75d36f&_nc_ohc=ZHxQ_dw1MvwQ7kNvwFgYP_h&_nc_oc=Adkybd2K0WJepK12tr8e_e_evPoGwlG98H6qvskRgDS2UeKQPpb_0eHP4y-pY2MrUC4&_nc_zt=23&_nc_ht=scontent-arn2-1.xx&_nc_gid=ibukK49uYkAz5BgwaobA7w&oh=00_AfPjhYS0dBvZ10IWMsBmGq4nirv5Vm8MdyKZFQ8StWdnVw&oe=684902BB", "url": "https://www.facebook.com/events/2270016540036844/", "js_timestamp": "2025-08-09T00:00:00+00:00", "formatted_start_date": "Saturday 09 August", "title": "L\u00e5ngholmen Afterparty"}, {"image_link": "https://scontent-arn2-1.xx.fbcdn.net/v/t39.30808-6/499718583_1218410380295239_3534100813690737262_n.jpg?_nc_cat=111&ccb=1-7&_nc_sid=75d36f&_nc_ohc=KqCRv2H8Z14Q7kNvwFHITNT&_nc_oc=AdlAJ57gRRBeS_KU85zjDbR8R1vtghlhoFzJH6Cboz2wRQLDe89k4x6cScxvrbnpr6E&_nc_zt=23&_nc_ht=scontent-arn2-1.xx&_nc_gid=cHIIGt30Y42xhIfyseqyLQ&oh=00_AfMP2hhm32oaLd1jVHsKh3RS49pf-Ey_xMTaF7ckCGPqJA&oe=68490F32", "url": "https://www.facebook.com/events/1341222007167008/", "js_timestamp": "2025-08-16T00:00:00+00:00", "formatted_start_date": "Saturday 16 August", "title": "BASTUFESTIVALEN // 16 AUG // Billie Jo, Dj Alban, Erik Veas, Franz J\u00e4ger, LAMACHINE, Psykoterapi \ud83e\udd21 "}, {"image_link": "https://scontent-arn2-1.xx.fbcdn.net/v/t39.30808-6/492895940_654750377344863_3356432772851983694_n.jpg?_nc_cat=110&ccb=1-7&_nc_sid=75d36f&_nc_ohc=x4TVTGK4eUsQ7kNvwFkGTx_&_nc_oc=AdmSvG8Oa-5RwD1QI9jmNOTO53tRIl0sqFpUFy8dxEgcuZbuKobCKpcJ5k9mQhIv7-s&_nc_zt=23&_nc_ht=scontent-arn2-1.xx&_nc_gid=EXwoxWC1SJeCwPLo2p7oIg&oh=00_AfNrRwYoZwEmYY_bIWW_nCalllNYyAHIZfj1ufC7rsYqng&oe=68490936", "url": "https://www.facebook.com/events/1420623902264145/", "js_timestamp": "2025-08-16T00:00:00+00:00", "formatted_start_date": "Saturday 16 August", "title": "THE ALEXSANDER \"AWARENESS\" - AV SHOW @ THE NODE"}, {"image_link": "https://billetto.imgix.net/c8uipiis8lmde2exzxqqht064ud6?w=1200&h=675&fit=crop&auto=compress%2Cformat&rect=0%2C0%2C1920%2C1080&s=dd3354dceda882d1164cfc81fb556f56", "url": "https://billetto.se/e/the-alexsander-awareness-av-show-the-node-biljetter-1271718?utm_campaign=websites&utm_content=SE+805283&utm_medium=publishers&utm_source=billetto+advertising", "js_timestamp": "2025-08-16T17:00:00+00:00", "formatted_start_date": "Saturday 16 August", "title": "THE ALEXSANDER \"AWARENESS\" - AV SHOW @ THE NODE"}, {"image_link": "https://billetto.imgix.net/si6x37fk04vdp3skupvh91jghqvl?w=1200&h=675&fit=crop&auto=compress%2Cformat&rect=0%2C49%2C1632%2C918&s=bb480a14d35e61ce70246d1260ffb51e", "url": "https://billetto.se/e/bastufestivalen-16-aug-billie-jo-dj-alban-erik-veas-franz-jager-lamachine-psykoterapi-biljetter-1304487?utm_campaign=websites&utm_content=SE+805283&utm_medium=publishers&utm_source=billetto+advertising", "js_timestamp": "2025-08-16T21:00:00+00:00", "formatted_start_date": "Saturday 16 August", "title": "BASTUFESTIVALEN: 16 AUG // Billie Jo, Dj Alban, Erik Veas, Franz J\u00e4ger, LAMACHINE, Psykoterapi."}, {"image_link": "https://scontent-arn2-1.xx.fbcdn.net/v/t39.30808-6/491263580_654790050674229_2849936021910933694_n.jpg?_nc_cat=106&ccb=1-7&_nc_sid=75d36f&_nc_ohc=4cmrygAN8BsQ7kNvwE0wK-3&_nc_oc=AdmxjRJb40BBdgqrFHyJLOJny70gyFcSRWHhu5N54v6Sbpn3ER7vMFUKW5Wamg-3KCg&_nc_zt=23&_nc_ht=scontent-arn2-1.xx&_nc_gid=1yd5inTq8t56mh6ecck4MQ&oh=00_AfPzOMPTrrWx5sp2BnGSGNp4zY6mfHQ7Mmw1wV3ozTXgcw&oe=6848DAF4", "url": "https://www.facebook.com/events/681708111488365/", "js_timestamp": "2025-08-23T00:00:00+00:00", "formatted_start_date": "Saturday 23 August", "title": "HYPNOTIC RHYTHM INVITES: TBA @ BIBLIOTEKET LIVE "}, {"image_link": "https://scontent-arn2-1.xx.fbcdn.net/v/t39.30808-6/499711316_1235763934600269_5807329177299725155_n.jpg?_nc_cat=104&ccb=1-7&_nc_sid=75d36f&_nc_ohc=QRQ_7UfxZbkQ7kNvwHI1bWU&_nc_oc=Adl6XUrADhlM4iSRLh9bjQn4TkP8MnPEnVqcR8kyuQCYT2Lb-z1O_a4RTlw2gCP2IWg&_nc_zt=23&_nc_ht=scontent-arn2-1.xx&_nc_gid=ZwPmvvrm99hqYJeNNLGHyg&oh=00_AfMtl-QyvIXRjEUsnKnBAfLC2z06O8iNMoC-ohDogQDgFA&oe=68490497", "url": "https://www.facebook.com/events/1692126671416971/", "js_timestamp": "2025-08-23T00:00:00+00:00", "formatted_start_date": "Saturday 23 August", "title": "M\u00e5nsken Open Air 2025"}, {"image_link": "https://billetto.imgix.net/kgd6sp8lqvq1g1vl4g123uj0e32n?w=1200&h=675&fit=crop&auto=compress%2Cformat&rect=651%2C37%2C6466%2C3637&s=a866bd106377cf6455c382dae3f1fdae", "url": "https://billetto.se/e/hypnotic-rhythm-invites-tba-biblioteket-live-biljetter-1285562?utm_campaign=websites&utm_content=SE+805283&utm_medium=publishers&utm_source=billetto+advertising", "js_timestamp": "2025-08-23T19:00:00+00:00", "formatted_start_date": "Saturday 23 August", "title": "HYPNOTIC RHYTHM INVITES: TBA - BIBLIOTEKET LIVE "}, {"image_link": "https://scontent-arn2-1.xx.fbcdn.net/v/t39.30808-6/490092042_1084951887004190_3268511734263866601_n.jpg?_nc_cat=107&ccb=1-7&_nc_sid=75d36f&_nc_ohc=pyC0yP86GF8Q7kNvwEr1eUz&_nc_oc=AdkuIBQVpnmuhgwPP7Ej2OKnnNn1WEZFtXtiMVXVoKMSdywANEMuEESTp7ADyf6NxkU&_nc_zt=23&_nc_ht=scontent-arn2-1.xx&_nc_gid=crOSxHrsO-CiJXBuUJ7dRw&oh=00_AfMjD21vzLKjAF_kuE1STcVOXH7AolC0hHg3aXJ_sC28Gw&oe=6848E9E8", "url": "https://www.facebook.com/events/1738167593694928/", "js_timestamp": "2025-08-29T00:00:00+00:00", "formatted_start_date": "Friday 29 August", "title": "The Shadow Of The Dark Shaman - Sanaton 20 Years Anniversary "}, {"image_link": "https://billetto.imgix.net/va7ge2ndkf6tggnwxshggyn2yfft?w=1200&h=675&fit=crop&auto=compress%2Cformat&rect=0%2C47%2C1000%2C563&s=f921dc4e67c7105c305786ca09c4fe04", "url": "https://billetto.se/e/klubb-dod-priest-hatif-biljetter-1300128?utm_campaign=websites&utm_content=SE+805283&utm_medium=publishers&utm_source=billetto+advertising", "js_timestamp": "2025-08-29T18:00:00+00:00", "formatted_start_date": "Friday 29 August", "title": "Klubb D\u00d6D: Priest + Hatif"}, {"image_link": "https://scontent-arn2-1.xx.fbcdn.net/v/t39.30808-6/489853003_1244243824251474_7184042939498194686_n.jpg?_nc_cat=105&ccb=1-7&_nc_sid=75d36f&_nc_ohc=Ldrvc4EeRYoQ7kNvwGB-y6s&_nc_oc=AdkPmU7sqYEfc3nTH_zYEaw70r7x8qNPVL3MYlHr7KzDmDRuqacqPkFGK3uyrrkxO1g&_nc_zt=23&_nc_ht=scontent-arn2-1.xx&_nc_gid=JZcUm_buqJ_itE_iOmqBMg&oh=00_AfNlYIAcT3bTDTFYI1qWsuTd4Yc2Del7pDMLZwHF7QRpIg&oe=6848FD1B", "url": "https://www.facebook.com/events/1224925955285784/", "js_timestamp": "2025-09-06T00:00:00+00:00", "formatted_start_date": "Saturday 06 September", "title": "NADIR 3.0"}, {"image_link": "https://billetto.imgix.net/bmub3au5bwjekr9k64jhdntrx4z0?w=1200&h=675&fit=crop&auto=compress%2Cformat&rect=0%2C0%2C800%2C450&s=80b6a5ff1b3c8664fdde91d511d5d547", "url": "https://billetto.se/e/brighter-death-now-desideii-marginis-raison-d-etre-hus-7-biljetter-1290159?utm_campaign=websites&utm_content=SE+805283&utm_medium=publishers&utm_source=billetto+advertising", "js_timestamp": "2025-09-17T17:00:00+00:00", "formatted_start_date": "Wednesday 17 September", "title": "Brighter Death Now + Desideii Marginis + Raison D\u2019etre | Hus 7"}, {"image_link": "https://billetto.imgix.net/z98fhvjvn1hm8uyu9bwelppi4dqo?w=1200&h=675&fit=crop&auto=compress%2Cformat&rect=0%2C143%2C800%2C450&s=01d6fae4c16df80c1ef7393444eec8d0", "url": "https://billetto.se/e/klubb-dod-ductape-tr-alvar-biljetter-1283052?utm_campaign=websites&utm_content=SE+805283&utm_medium=publishers&utm_source=billetto+advertising", "js_timestamp": "2025-09-20T18:00:00+00:00", "formatted_start_date": "Saturday 20 September", "title": "Klubb D\u00d6D: Ductape (TR) + Alvar"}, {"image_link": "https://scontent-arn2-1.xx.fbcdn.net/v/t39.30808-6/484327929_951065930434756_8484817570370135929_n.jpg?_nc_cat=108&ccb=1-7&_nc_sid=75d36f&_nc_ohc=8_yQH7vIkCAQ7kNvwFEHKMz&_nc_oc=AdkQx8Tlx0tZQ-AytffXr5bwTaVKSVjoYIsjaT4Fp47KxfhZPV-OCQqjpSNpIXjFAjI&_nc_zt=23&_nc_ht=scontent-arn2-1.xx&_nc_gid=F3fFzh3GOV-ew-kHoA-hqw&oh=00_AfOTaP-5HjJRloaFGiaPBl1oXwNpKYdTRHQKza5enerbmA&oe=6848EAC3", "url": "https://www.facebook.com/events/605784379024165/", "js_timestamp": "2025-10-05T00:00:00+00:00", "formatted_start_date": "Sunday 05 October", "title": "Kruder & Dorfmeister LIVE / Berns"}, {"image_link": "https://scontent-arn2-1.xx.fbcdn.net/v/t39.30808-6/500730884_1249792453823095_5490146322416028804_n.jpg?_nc_cat=106&ccb=1-7&_nc_sid=75d36f&_nc_ohc=jT0RL2z7m5EQ7kNvwFF4VVf&_nc_oc=AdmFO_h8Sd1hB921Qy28TVEN2xNBisKYqNm1-5-OcpgzbROlMZSyV9b-xC9BuNbnN7k&_nc_zt=23&_nc_ht=scontent-arn2-1.xx&_nc_gid=z8VP1LfRUAbuGYCQzLYWEA&oh=00_AfN9-S2sbPJhUGhS6yfJoCp_oc_lXUo3dAqY2aYBqrq3Kw&oe=6848EA3D", "url": "https://www.facebook.com/events/728324496197817/", "js_timestamp": "2025-10-11T00:00:00+00:00", "formatted_start_date": "Saturday 11 October", "title": "HOZHO (3 hour set) | Stockholm"}, {"image_link": "https://billetto.imgix.net/h8eey5oka61nk0veh1d07lsp9zk2?w=1200&h=675&fit=crop&auto=compress%2Cformat&rect=0%2C0%2C1920%2C1080&s=2dd12fc7f2e154597c7426be9dba69f5", "url": "https://billetto.se/e/hozho-3-hour-dj-set-slaktkyrkan-biljetter-1300031?utm_campaign=websites&utm_content=SE+805283&utm_medium=publishers&utm_source=billetto+advertising", "js_timestamp": "2025-10-11T20:00:00+00:00", "formatted_start_date": "Saturday 11 October", "title": "HOZHO 3 hour dj-set | Slaktkyrkan"}, {"image_link": "https://scontent-arn2-1.xx.fbcdn.net/v/t39.30808-6/486103891_964594059081943_683433205934673538_n.jpg?_nc_cat=103&ccb=1-7&_nc_sid=75d36f&_nc_ohc=JLT6ohYCHgUQ7kNvwFL3Kl6&_nc_oc=Adk1U0CykX6wVlA7evYd8Pp3Dlf3TGm3nItyrztKVt1WNhQUwlQrjDFunas2Ejdwh_8&_nc_zt=23&_nc_ht=scontent-arn2-1.xx&_nc_gid=SGi1XDKeHsF8suUFzSENWg&oh=00_AfNVj0diMI0TI_PbUK9_nCVndALBsS0VP1C0koTz8OQVUg&oe=6848F332", "url": "https://www.facebook.com/events/1169032131015903/", "js_timestamp": "2025-10-19T00:00:00+00:00", "formatted_start_date": "Sunday 19 October", "title": "Fatboy Slim | Stockholm"}, {"image_link": "https://scontent-arn2-1.xx.fbcdn.net/v/t39.30808-6/495744595_1270124171790419_8251080086220736336_n.jpg?_nc_cat=105&ccb=1-7&_nc_sid=75d36f&_nc_ohc=JNDP__tA-sYQ7kNvwHjzyfn&_nc_oc=Adl44y8miyBO3ISLLIcE4zjXk6VA_YDsICuL2cWbMYNv4nLGCQl3_Z5M_EI7qjAJlGk&_nc_zt=23&_nc_ht=scontent-arn2-1.xx&_nc_gid=XC6Xqs1J4ocNaDTq0gQezw&oh=00_AfNIJ6WEDy-V02C2Ek5vFllf1sqZUKXmw4c_LeYw3yBV-g&oe=68490033", "url": "https://www.facebook.com/events/569852742389391/", "js_timestamp": "2025-11-01T00:00:00+00:00", "formatted_start_date": "Saturday 01 November", "title": "Psychedelic Halloween 2"}, {"image_link": "https://scontent-arn2-1.xx.fbcdn.net/v/t39.30808-6/500080351_1116568797170443_7092546636738067695_n.jpg?_nc_cat=107&ccb=1-7&_nc_sid=75d36f&_nc_ohc=PfZqH0q7-DMQ7kNvwECTm9g&_nc_oc=Admr6aZTH1WqGczepMNnW19B25vx9WTaYXGgytcAdXByhyj4ncm1CxCBoNtcIy5eEzo&_nc_zt=23&_nc_ht=scontent-arn2-1.xx&_nc_gid=N6qGLc4-gjzaL6J47tNE0A&oh=00_AfP1eUhj93QDNA5K6S2vTgBUduJHwB7YkAP2ogh1KucGtA&oe=68490536", "url": "https://www.facebook.com/events/702821318793210/", "js_timestamp": "2025-11-07T00:00:00+00:00", "formatted_start_date": "Friday 07 November", "title": "Monday Bar Family Cruise 2025 (no 63)"}, {"image_link": "https://billetto.imgix.net/kzxg7anb6vx04bgt2zxe308rmq0u?w=1200&h=675&fit=crop&auto=compress%2Cformat&rect=0%2C0%2C800%2C450&s=48332b214378e7523a41780e811d81e8", "url": "https://billetto.se/e/a-maze-celebration-indoors-biljetter-1088710?utm_campaign=websites&utm_content=SE+805283&utm_medium=publishers&utm_source=billetto+advertising", "js_timestamp": "2025-11-29T21:00:00+00:00", "formatted_start_date": "Saturday 29 November", "title": "A-MAZE CELEBRATION - (INDOORS)"}, {"image_link": "https://scontent-arn2-1.xx.fbcdn.net/v/t39.30808-6/486601168_1072024878296891_6187624657396284496_n.jpg?_nc_cat=106&ccb=1-7&_nc_sid=75d36f&_nc_ohc=pOeBNPaxJS0Q7kNvwGTN782&_nc_oc=Adn3eUHPo0rIqbHDSvBO8pUMWQNPI3jVKs6Nnmx0MN3XAzGmiVWVdC4bVEO73cDsHUM&_nc_zt=23&_nc_ht=scontent-arn2-1.xx&_nc_gid=p98Vik0xh3KDIhj8aeVEUA&oh=00_AfO6KriCh4OlRxFOJOXHG_Z-8aN57BavUlorpXvI6b8KAw&oe=68490E97", "url": "https://www.facebook.com/events/1212853129806741/", "js_timestamp": "2025-12-06T00:00:00+00:00", "formatted_start_date": "Saturday 06 December", "title": "The Shadow Of The Dark Shaman - 50 Trips around the sun"}, {"image_link": "https://scontent-arn2-1.xx.fbcdn.net/v/t39.30808-6/472361317_2124834517975536_3293979273445093415_n.jpg?_nc_cat=109&ccb=1-7&_nc_sid=75d36f&_nc_ohc=WdZuVS_aQ0EQ7kNvwGjf41N&_nc_oc=AdkB6hs44DxPP78G9MoGmjjL4k2fN_GUaVXl5p5morZcJrqNFLRhrYfykGAMH0cqWqg&_nc_zt=23&_nc_ht=scontent-arn2-1.xx&_nc_gid=pfXKJu6F5O6lKBMSqUa_mA&oh=00_AfOThthd_xh_SLuauV_Zma5PmN0JkNWWapCgdO4KWCu_xg&oe=6849016D", "url": "https://www.facebook.com/events/1717214878473377/", "js_timestamp": "2026-07-17T00:00:00+00:00", "formatted_start_date": "Friday 17 July", "title": "Demand Festival 2024 "}]